FaucetPy/__init__.py
FaucetPy/api.py
FaucetPy/merchant.py
FaucetPy-0.2.1.dist-info/LICENSE
FaucetPy-0.2.1.dist-info/METADATA
FaucetPy-0.2.1.dist-info/WHEEL
FaucetPy-0.2.1.dist-info/top_level.txt
FaucetPy-0.2.1.dist-info/RECORD
