Metadata-Version: 2.1
Name: FaucetPy
Version: 0.2.1
Summary: FaucetPay + Python = FaucetPy
Home-page: https://github.com/HanzHaxors/FaucetPy
Author: HanzHaxors
Author-email: hanzhaxors@gmail.com
License: BSD 2-clause
Platform: UNKNOWN
Classifier: License :: OSI Approved :: BSD License
Classifier: Operating System :: POSIX :: Linux
Classifier: Intended Audience :: Developers
Classifier: Intended Audience :: Financial and Insurance Industry
Requires-Dist: requests (==2.25.1)
